{
    "_active": true,
    "_notice_text": "Noch kein aktueller Hinweis",
    "_plus_required": false,
    "_plus_store_url": null,
    "_support_contract": false,
    "_version_required": 0,
    "account_supported": true,
    "api": "koha",
    "city": "Burghausen/Sal",
    "country": "Deutschland",
    "data": {
        "baseurl": "https://sb-burghausen.lmscloud.net",
        "libopacplus": true,
        "onleihe": "https://biblioload.onleihe.de/verbund_burghausen",
        "onleihe_libraryId": "366"
    },
    "displayname": "Stadtbibliothek Burghausen",
    "geo": [
        48.15823,
        12.83324
    ],
    "information": "https://info.opacapp.de/burghausen.html",
    "library_id": 2025,
    "state": "Bayern",
    "title": "Stadtbibliothek"
}