{
    "_active": true,
    "_notice_text": "Zutritt: \r\n\r\n\u2022\tvollst\u00e4ndig Geimpfte (mindestens zweimal geimpft) ohne Begrenzung des nach der Impfung vergangenen Zeitraums\r\n\u2022\tGenesene, deren Nachweis nicht \u00e4lter als drei Monate ist (Erster positiver PCR Test darf h\u00f6chstens 90 Tage zur\u00fcckliegen)\r\n\u2022\tKinder bis einschlie\u00dflich 7 Jahre, die noch nicht eingeschult sind.\r\n\u2022\tGrundsch\u00fcler*innen, Sch\u00fcler*innen eines sonderp\u00e4dagogischen Bildungs- und Beratungszentrums, einer auf der Grundschule aufbauenden Schule oder einer beruflichen Schule \u2013 gilt nur f\u00fcr Sch\u00fcler*innen bis einschlie\u00dflich 17 Jahre\r\n\r\nMit Antigen-Schnelltest (max. 24 Stunden g\u00fcltig) oder PCR-Test (max. 48 Stunden g\u00fcltig)\r\n\r\n\u2022\tPersonen bis einschlie\u00dflich 17 Jahre, die nicht mehr zur Schule gehen\r\n\u2022\tPersonen, die sich aus medizinischen Gr\u00fcnden nicht impfen lassen k\u00f6nnen (\u00e4rztlicher Nachweis notwendig)\r\n\u2022\tPersonen, f\u00fcr die es keine allgemeine Impfempfehlung der St\u00e4ndigen\r\nImpfkommission (STIKO) gibt\r\n\r\nRegelung f\u00fcr Sch\u00fclerinnen und Sch\u00fcler bis 17 Jahre:\r\n\r\n\u2022\tals Nachweis der Testung gilt der Sch\u00fclerausweis\r\n\r\n\r\nAktuelle Details zu den Zugangsregelungen finden Sie auf www.stadtbibliothek.freiburg.de\r\n\r\n***\r\n\r\nDie automatische Au\u00dfenr\u00fcckgabe in der Hauptstelle ist ge\u00f6ffnet:\r\n\r\n    Montag: 6 - 23 Uhr\r\n    Dienstag - Freitag: 6 - 10 Uhr, 19 - 23 Uhr\r\n    Samstag: 6 - 10 Uhr, 15 - 23 Uhr\r\n    Sonntag: 6 - 23\r\n\r\n***\r\n\r\nInfos zu unseren digitalen Angeboten finden Sie unter www.stadtbibliothek.freiburg.de\r\n\r\n***\r\n\r\nOnline-Bezahlung auf www.stadtbibliothek.freiburg.de ist m\u00f6glich - f\u00fcr die Freischaltung zur neuen Jahresgeb\u00fchr kontaktieren Sie uns unter 0761 / 201-2207 oder stadtbibliothek@stadt.freiburg.de",
    "_plus_required": false,
    "_plus_store_url": "https://play.google.com/store/apps/details?id=de.opacapp.freiburg",
    "_support_contract": true,
    "_version_required": 0,
    "account_supported": true,
    "api": "sisis",
    "city": "Freiburg (Breisgau)",
    "country": "Deutschland",
    "data": {
        "baseurl": "https://katalog.stadtbibliothek.freiburg.de/webOPACClient",
        "libopacplus": true,
        "onleihe": "http://www3.onleihe.de/freiburg",
        "onleihe_libraryId": "145",
        "onleihe_singleLibrary": true,
        "suppress_fee_warnings": true
    },
    "displayname": "Stadtbibliothek Freiburg",
    "geo": [
        47.9960214,
        7.8532714
    ],
    "information": "https://info.opacapp.de/freiburg.html",
    "library_id": 8668,
    "state": "Baden-W\u00fcrttemberg",
    "title": "Stadtbibliothek"
}