{
    "_active": true,
    "_notice_text": "Zutritt nur f\u00fcr nachweislich Geimpfte, Genesene und Getestete!\r\nKinder & Sch\u00fcler gelten als getestet.\r\nZutritt nur mit OP-Maske\r\nEs gelten die \u00fcblichen Abstands- und Hygieneregeln!",
    "_plus_required": false,
    "_plus_store_url": "https://play.google.com/store/apps/details?id=de.opacapp.kaufbeuren",
    "_support_contract": true,
    "_version_required": 0,
    "account_supported": true,
    "api": "sisis",
    "city": "Kaufbeuren",
    "country": "Deutschland",
    "data": {
        "baseurl": "https://buch.kaufbeuren.de/webOPACClient",
        "startparams": "Login=opacint"
    },
    "displayname": "Stadtb\u00fccherei Kaufbeuren",
    "geo": [
        47.8830175,
        10.625966
    ],
    "information": "https://info.opacapp.de/kaufbeuren.html",
    "library_id": 4334,
    "state": "Bayern",
    "title": "Stadtb\u00fccherei"
}