{
    "_active": true,
    "_notice_text": null,
    "_plus_required": false,
    "_plus_store_url": null,
    "_support_contract": false,
    "_version_required": 0,
    "account_supported": false,
    "api": "winbiap",
    "city": "Kriftel",
    "country": "Deutschland",
    "data": {
        "baseurl": "https://webopac.winbiap.de/kriftel"
    },
    "geo": null,
    "information": "https://webopac.winbiap.de/kriftel/index.aspx",
    "library_id": 4689,
    "state": "Hessen",
    "title": "Gemeindeb\u00fccherei"
}