{
    "_active": true,
    "_notice_text": null,
    "_plus_required": false,
    "_plus_store_url": null,
    "_support_contract": false,
    "_version_required": 0,
    "account_supported": true,
    "api": "sisis",
    "city": "M\u00fclheim an der Ruhr",
    "country": "Deutschland",
    "data": {
        "baseurl": "https://katalog.hs-ruhrwest.de/webOPACClient.nmbsis",
        "startparams": "Login=wonmbmue"
    },
    "geo": [
        51.449266,
        6.869062
    ],
    "information": "http://www.hochschule-ruhr-west.de/campus/bibliothek/oeffnungszeiten.html",
    "library_id": 9089,
    "state": "Nordrhein-Westfalen",
    "title": "Hochschule Ruhr West"
}