{
    "_active": true,
    "_notice_text": null,
    "_plus_required": false,
    "_plus_store_url": null,
    "_support_contract": false,
    "_version_required": 0,
    "account_supported": true,
    "api": "adis",
    "city": "M\u00fcnchen",
    "country": "Deutschland",
    "data": {
        "baseurl": "https://ssl.muenchen.de/aDISWeb/app",
        "customssl": true,
        "startparams": "service=direct/0/Home/$DirectLink&sp=SOPAC"
    },
    "geo": [
        48.1312944,
        11.5912184
    ],
    "information": "http://www.muenchner-stadtbibliothek.de/info-service/",
    "library_id": 8734,
    "state": "Bayern",
    "title": "M\u00fcnchner Stadtbibliothek"
}