{
    "_active": true,
    "_notice_text": null,
    "_plus_required": false,
    "_plus_store_url": null,
    "_support_contract": false,
    "_version_required": 0,
    "account_supported": true,
    "api": "webopac.net",
    "city": "Neerach",
    "country": "Schweiz",
    "data": {
        "baseurl": "http://www.bibliotheken-zh.ch/Neerach"
    },
    "geo": [
        47.5125,
        8.47301
    ],
    "information": "http://www.primarschule-neerach.ch/mediothek/",
    "library_id": 9107,
    "state": "Z\u00fcrich",
    "title": "Mediothek"
}