{
    "_active": true,
    "_notice_text": "",
    "_plus_required": false,
    "_plus_store_url": null,
    "_support_contract": false,
    "_version_required": 0,
    "account_supported": true,
    "api": "sisis",
    "city": "Remscheid",
    "country": "Deutschland",
    "data": {
        "baseurl": "https://webopac.remscheid.de/webOPACClient.remscheid"
    },
    "geo": [
        51.1819294,
        7.1893905
    ],
    "information": "http://www.remscheid.de/freizeit-und-kultur/bibliothek/bibliothek.php",
    "library_id": 8760,
    "state": "Nordrhein-Westfalen",
    "title": "Stadtbibliothek"
}