{
    "_active": true,
    "_notice_text": "Der Besuch der Stadtbibliothek ist aktuell nur mit einem negativen Testnachweis oder Impf- bzw. Genesenen-Nachweis m\u00f6glich. Kinder bis 6 Jahren sind von den Beschr\u00e4nkungen ausgenommen. Dies gilt auch f\u00fcr Sch\u00fclerinnen und Sch\u00fcler bis einschlie\u00dflich 17 Jahre w\u00e4hrend des Schulbetriebs. In den Ferien ist ein Test vorzulegen. Personen ab 18 Jahren m\u00fcssen in den R\u00e4umen der Bibliothek eine FFP2-Maske tragen. Wenn Sie nur kurz etwas abholen, abgeben oder bezahlen m\u00f6chten, dann ist ein Nachweis weiterhin nicht notwendig.\r\n\r\nBitte beachten Sie, dass die Bibliothek am Fasnets-Dienstag, 01.03.2022, ganzt\u00e4gig geschlossen bleibt. Der R\u00fcckgabekasten ist von Samstagmittag, 26.02.2022, bis einschlie\u00dflich Dienstag, 01.03.2022, ebenfalls geschlossen.\r\nW\u00e4hrend der restlichen Fasnetsferien sind wir gerne zu den regul\u00e4ren \u00d6ffnungszeiten f\u00fcr Sie da. Bitte beachten Sie, dass Sch\u00fclerinnen und Sch\u00fcler w\u00e4hrend der Ferien einen negativen Testnachweis vorlegen m\u00fcssen f\u00fcr den Bibliotheksbesuch (Antigentest max. 24h, PCR-Test max. 48h).",
    "_plus_required": false,
    "_plus_store_url": "https://play.google.com/store/apps/details?id=de.opacapp.sigmaringen",
    "_support_contract": true,
    "_version_required": 0,
    "account_supported": true,
    "api": "open",
    "city": "Sigmaringen",
    "country": "Deutschland",
    "data": {
        "baseurl": "https://bibliothek.komm.one/sigmaringen",
        "libopacplus": true,
        "onleihe": "https://www.onleihe.de/schwalbe",
        "onleihe_libraryId": "400",
        "urls": {
            "account": "Konto",
            "advanced_search": "Mediensuche/erweiterte-Suche",
            "new_acq": "Neuerwerbungen",
            "simple_search": "Mediensuche/einfache-Suche"
        }
    },
    "geo": [
        48.0856157,
        9.2162056
    ],
    "information": "https://info.opacapp.net/sigmaringen.html",
    "library_id": 7270,
    "state": "Baden-W\u00fcrttemberg",
    "title": "Stadtbibliothek"
}